acace_web_interface/__init__.py
acace_web_interface-0.1.0.dist-info/METADATA
acace_web_interface-0.1.0.dist-info/WHEEL
acace_web_interface-0.1.0.dist-info/RECORD
